{
  "data_type": "tabular",
  "model_type": "mlp",
  "task_type": "classification", 
  "target_column": "target", 
  "feature_columns": null, 
  "normalize": true,
  "hidden_dims": [128, 64],
  "dropout": 0.3,
  "batch_size": 32,
  "learning_rate": 0.001,
  "num_epochs": 50,
  "optimizer_config": {
    "optimizer_type": "adam",
    "learning_rate": 0.001,
    "weight_decay": 0.0001 
  },
  "scheduler_config": {
    "scheduler_type": "step",
    "step_size": 15,
    "gamma": 0.1
  },
  "early_stopping": {
    "patience": 10,
    "min_delta": 0.001,
    "restore_best_weights": true
  },
  "train_ratio": 0.7,
  "val_ratio": 0.15,
  "test_ratio": 0.15,
  "num_workers": 0,

  "input_dim": null,
  "num_classes": null
} 